DivarApi/__init__.py
DivarApi/core.py
DivarApi-0.0.3.dist-info/LICENSE
DivarApi-0.0.3.dist-info/METADATA
DivarApi-0.0.3.dist-info/WHEEL
DivarApi-0.0.3.dist-info/top_level.txt
DivarApi-0.0.3.dist-info/RECORD
