Metadata-Version: 2.1
Name: DivarApi
Version: 0.0.3
Summary: Unofficial api of Divar - by Reverse Engineering
Author: RealPalas
Author-email: palasongithub@gmail.com
Keywords: python,divar,api,iran,web scraping,bot,palas
Classifier: Development Status :: 1 - Planning
Classifier: Intended Audience :: Developers
Classifier: Programming Language :: Python :: 3
Classifier: Operating System :: Unix
Classifier: Operating System :: MacOS :: MacOS X
Classifier: Operating System :: Microsoft :: Windows
Requires-Python: >=3.9
License-File: LICENSE
Requires-Dist: requests
Requires-Dist: beautifulsoup4
Requires-Dist: jwt
